fir/fir_eda_sim_files/design.sv
// Code your design here
module fir_filter (
    data_in, data_out, clk, rst
);
    output[17:0] data_out;
    input[7:0] data_in;
    input clk, rst;

    parameter b0 = 8'b01010101;
    parameter b1 = 8'b01001111;
    parameter b2 = 8'b00000000;
    parameter b3 = 8'b01001111;
    parameter b4 = 8'b11111111;
    parameter b5 = 8'b01001111;
    parameter b6 = 8'b00000000;
    parameter b7 = 8'b01001111;
    parameter b8 = 8'b01010101;


    reg[17:0] ff_data[1:8];

    assign data_out = b0*data_in+b1*ff_data[1]+b2*ff_data[2]+b3*ff_data[3]+b4*ff_data[4]+b5*ff_data[5]+b6*ff_data[6]+b7*ff_data[7]+b8*ff_data[8];

    integer k;
    always @ (posedge clk)
        if (rst==1)
        begin
            for (k=1;k<=8;k=k+1)
            begin
                ff_data[k]<=0;
            end
        end

        else
        begin
          	ff_data[1]<=data_in;
            for (k=2;k<=8;k=k+1)
            begin
                ff_data[k]<=ff_data[k-1];
            end
        end
    
endmodule

fir/fir_eda_sim_files/testbench.sv
// Code your testbench here
// or browse Examples
`timescale 1ns/10ps
module filter_testbench;

	reg[7:0] data_in;
	reg clk, rst;
  	wire[17:0] data_out;


    fir_filter filter1(  //Chevychev_highpass instead of fir_filter for iir
        .data_in(data_in), 
        .data_out(data_out), 
        .clk(clk), 
        .rst(rst)
    );
    

    initial 
        begin
           clk = 1'b0;
	   forever 
            begin
                #10416 clk = ~clk;
                if (clk == 1)
                  begin
                  	$display(data_out);
                  end
            end  
        end

	initial
	begin
        #0      rst=1;
                data_in=8'b00000000;
        #20832  rst=0;
        #20833  data_in=8'b00000000;
        #20834  data_in=8'b11111010;
        #20833  data_in=8'b11111111;
        #20834  data_in=8'b01010100;
        #20833  data_in=8'b00001010;
        #20834  data_in=8'b01111111;
        #20833  data_in=8'b11101000;
        #20834  data_in=8'b01111010;
        #20833  data_in=8'b01101010;
        #20834  data_in=8'b10101100;
        #20833  data_in=8'b00000000;
        #20834  data_in=8'b10101100;
        #20833  data_in=8'b01101010;
        #20834  data_in=8'b01111010;
        #20833  data_in=8'b11101000;
        #20834  data_in=8'b01111111;
        #20833  data_in=8'b00001010;
        #20834  data_in=8'b01010100;
        #20833  data_in=8'b11111111;
        #20834  data_in=8'b11111010;
        #20833  data_in=8'b00000000;
        #20834  data_in=8'b11111010;
        #20833  data_in=8'b11111111;
        #20834  data_in=8'b01010100;
        #20833  data_in=8'b00001010;
        #20834  data_in=8'b01111111;
        #20833  data_in=8'b11101000;
        #20834  data_in=8'b01111010;
        #20833  data_in=8'b01101010;
        #20834  data_in=8'b10101100;
        #20833  data_in=8'b00000000;
        #20834  data_in=8'b10101100;
        #20833  data_in=8'b01101010;
        #20834  data_in=8'b01111010;
        #20833  data_in=8'b11101000;
        #20834  data_in=8'b01111111;
        #20833  data_in=8'b00001010;
        #20834  data_in=8'b01010100;
        #20833  data_in=8'b11111111;
        #20834  data_in=8'b11111010;
        #20833  data_in=8'b00000000;
        #20834  data_in=8'b11111010;
        #20833  data_in=8'b11111111;
        #20834  data_in=8'b01010100;
        #20833  data_in=8'b00001010;
        #20834  data_in=8'b01111111;
        #20833  data_in=8'b11101000;
        #20834  data_in=8'b01111010;
        #20833  data_in=8'b01101010;
        #20834  data_in=8'b10101100;
        #20833  data_in=8'b00000000;
        #20834  data_in=8'b10101100;
        #20833  data_in=8'b01101010;
        #20834  data_in=8'b01111010;
        #20833  data_in=8'b11101000;
        #20834  data_in=8'b01111111;
        #20833  data_in=8'b00001010;
        #20834  data_in=8'b01010100;
        #20833  data_in=8'b11111111;
        #20834  data_in=8'b11111010;
        #20833  data_in=8'b00000000;
        #20834  data_in=8'b11111010;
        #20833  data_in=8'b11111111;
        #20834  data_in=8'b01010100;
        #20833  data_in=8'b00001010;
        #20834  data_in=8'b01111111;
        #20833  data_in=8'b11101000;
        #20834  data_in=8'b01111010;
        #20833  data_in=8'b01101010;
        #20834  data_in=8'b10101100;
        #20833  data_in=8'b00000000;
        #20834  data_in=8'b10101100;
        #20833  data_in=8'b01101010;
        #20834  data_in=8'b01111010;
        #20833  data_in=8'b11101000;
        #20834  data_in=8'b01111111;
        #20833  data_in=8'b00001010;
        #20834  data_in=8'b01010100;
        #20833  data_in=8'b11111111;
        #20834  data_in=8'b11111010;
        #20833  data_in=8'b00000000;
        #20834  data_in=8'b11111010;
        #20833  data_in=8'b11111111;
        #20834  data_in=8'b01010100;
        #20833  data_in=8'b00001010;
        #20834  data_in=8'b01111111;
        #20833  data_in=8'b11101000;
        #20834  data_in=8'b01111010;
        #20833  data_in=8'b01101010;
        #20834  data_in=8'b10101100;
        #20833  data_in=8'b00000000;
        #20834  data_in=8'b10101100;
        #20833  data_in=8'b01101010;
        #20834  data_in=8'b01111010;
        #20833  data_in=8'b11101000;
        #20834  data_in=8'b01111111;
	    #20832  $stop;
	end

	initial 
	begin
		$dumpfile("filter_dump.vcd");
		$dumpvars;
	end
endmodule

fir/fir_eda_sim_files/filter_dump.vcd
$date
    Mar  6, 2023  06:11:33
$end
$version
    TOOL:	xmsim	20.09-s003
$end
$timescale
    10 ps
$end

$scope module filter_testbench $end
$var reg       8 !    data_in [7:0] $end
$var reg       1 "    clk $end
$var reg       1 #    rst $end
$var wire     18 $    data_out [17:0] $end

$scope module filter1 $end
$var wire     18 $    data_out [17:0] $end
$var wire      8 %    data_in [7:0] $end
$var wire      1 &    clk  $end
$var wire      1 '    rst  $end
$var parameter  8 (    b0 $end
$var parameter  8 )    b1 $end
$var parameter  8 *    b2 $end
$var parameter  8 +    b3 $end
$var parameter  8 ,    b4 $end
$var parameter  8 -    b5 $end
$var parameter  8 .    b6 $end
$var parameter  8 /    b7 $end
$var parameter  8 0    b8 $end
$var reg      18 1    ff_data[1] [17:0] $end
$var reg      18 2    ff_data[2] [17:0] $end
$var reg      18 3    ff_data[3] [17:0] $end
$var reg      18 4    ff_data[4] [17:0] $end
$var reg      18 5    ff_data[5] [17:0] $end
$var reg      18 6    ff_data[6] [17:0] $end
$var reg      18 7    ff_data[7] [17:0] $end
$var reg      18 8    ff_data[8] [17:0] $end
$var integer  32 9    k $end
$upscope $end

$upscope $end

$enddefinitions $end
$dumpvars
b1010101 0
b1001111 /
b0 .
b1001111 -
b11111111 ,
b1001111 +
b0 *
b1001111 )
b1010101 (
b0 !
0"
1#
bx $
b0 %
0&
1'
bx 1
bx 2
bx 3
bx 4
bx 5
bx 6
bx 7
bx 8
bx 9
$end
#1041600
1"
1&
b1 9
b10 9
b11 9
b100 9
b101 9
b110 9
b111 9
b1000 9
b1001 9
b0 1
b0 2
b0 3
b0 4
b0 5
b0 6
b0 7
b0 8
b0 $
#2083200
0#
0"
0&
0'
#3124800
1"
1&
b10 9
b11 9
b100 9
b101 9
b110 9
b111 9
b1000 9
b1001 9
#4166400
0"
0&
#5208000
1"
1&
#6249600
0"
0&
#6249900
b11111010 !
b11111010 %
b101001100000010 $
#7291200
1"
1&
b10 9
b11 9
b100 9
b101 9
b110 9
b111 9
b1000 9
b1001 9
b11111010 1
b1010000000101000 $
#8332800
0"
0&
#8333200
b11111111 !
b11111111 %
b1010000111010001 $
#9374400
1"
1&
b10 9
b11 9
b100 9
b101 9
b110 9
b111 9
b1000 9
b1001 9
b11111111 1
b11111010 2
b1010001101011100 $
#10416000
0"
0&
#10416600
b1010100 !
b1010100 %
b110101010010101 $
#11457600
1"
1&
b10 9
b11 9
b100 9
b101 9
b110 9
b111 9
b1000 9
b1001 9
b1010100 1
b11111111 2
b11111010 3
b1000001011110110 $
#12499200
0"
0&
#12499900
b1010 !
b1010 %
b110101001100100 $
#13540800
1"
1&
b10 9
b11 9
b100 9
b101 9
b110 9
b111 9
b1000 9
b1001 9
b1010 1
b1010100 2
b11111111 3
b11111010 4
b10100111000011111 $
#14582400
0"
0&
#14583300
b1111111 !
b1111111 %
b10111010011111000 $
#15624000
1"
1&
b10 9
b11 9
b100 9
b101 9
b110 9
b111 9
b1000 9
b1001 9
b1111111 1
b1010 2
b1010100 3
b11111111 4
b11111010 5
b11011011001101111 $
#16665600
0"
0&
#16666600
b11101000 !
b11101000 %
b11101100101001100 $
#17707200
1"
1&
b10 9
b11 9
b100 9
b101 9
b110 9
b111 9
b1000 9
b1001 9
b11101000 1
b1111111 2
b1010 3
b1010100 4
b11111111 5
b11111010 6
b10011101000010011 $
#18748800
0"
0&
#18750000
b1111010 !
b1111010 %
b10001010110001101 $
#19790400
1"
1&
b10 9
b11 9
b100 9
b101 9
b110 9
b111 9
b1000 9
b1001 9
b1111010 1
b11101000 2
b1111111 3
b1010 4
b1010100 5
b11111111 6
b11111010 7
b1110011001100001 $
#20832000
0"
0&
#20833300
b1101010 !
b1101010 %
b1110000100010001 $
#21873600
1"
1&
b10 9
b11 9
b100 9
b101 9
b110 9
b111 9
b1000 9
b1001 9
b1101010 1
b1111010 2
b11101000 3
b1111111 4
b1010 5
b1010100 6
b11111111 7
b11111010 8
b11010111011001010 $
#22915200
0"
0&
#22916700
b10101100 !
b10101100 %
b11100010010110100 $
#23956800
1"
1&
b10 9
b11 9
b100 9
b101 9
b110 9
b111 9
b1000 9
b1001 9
b10101100 1
b1101010 2
b1111010 3
b11101000 4
b1111111 5
b1010 6
b1010100 7
b11111111 8
b100001000010110110 $
#24998400
0"
0&
#25000000
b0 !
b0 %
b11101011110011010 $
#26040000
1"
1&
b10 9
b11 9
b100 9
b101 9
b110 9
b111 9
b1000 9
b1001 9
b0 1
b10101100 2
b1101010 3
b1111010 4
b11101000 5
b1111111 6
b1010 7
b1010100 8
b10000000011001110 $
#27081600
0"
0&
#27083400
b10101100 !
b10101100 %
b10011100111101010 $
#28123200
1"
1&
b10 9
b11 9
b100 9
b101 9
b110 9
b111 9
b1000 9
b1001 9
b10101100 1
b0 2
b10101100 3
b1101010 4
b1111010 5
b11101000 6
b1111111 7
b1010 8
b10101110100000011 $
#29164800
0"
0&
#29166700
b1101010 !
b1101010 %
b10100011100011001 $
#30206400
1"
1&
b10 9
b11 9
b100 9
b101 9
b110 9
b111 9
b1000 9
b1001 9
b1101010 1
b10101100 2
b0 3
b10101100 4
b1101010 5
b1111010 6
b11101000 7
b1111111 8
b11000000110110101 $
#31248000
0"
0&
#31250100
b1111010 !
b1111010 %
b11000011100000101 $
#32289600
1"
1&
b10 9
b11 9
b100 9
b101 9
b110 9
b111 9
b1000 9
b1001 9
b1111010 1
b1101010 2
b10101100 3
b0 4
b10101100 5
b1101010 6
b1111010 7
b11101000 8
b10010101011111110 $
#33331200
0"
0&
#33333400
b11101000 !
b11101000 %
b10100111110000100 $
#34372800
1"
1&
b10 9
b11 9
b100 9
b101 9
b110 9
b111 9
b1000 9
b1001 9
b11101000 1
b1111010 2
b1101010 3
b10101100 4
b0 5
b10101100 6
b1101010 7
b1111010 8
b11010100111100010 $
#35414400
0"
0&
#35416800
b1111111 !
b1111111 %
b11000011100000101 $
#36456000
1"
1&
b10 9
b11 9
b100 9
b101 9
b110 9
b111 9
b1000 9
b1001 9
b1111111 1
b11101000 2
b1111010 3
b1101010 4
b10101100 5
b0 6
b10101100 7
b1101010 8
b10110110111110010 $
#37497600
0"
0&
#37500100
b1010 !
b1010 %
b10100011100011001 $
#38539200
1"
1&
b10 9
b11 9
b100 9
b101 9
b110 9
b111 9
b1000 9
b1001 9
b1010 1
b1111111 2
b11101000 3
b1111010 4
b1101010 5
b10101100 6
b0 7
b10101100 8
b10010000101011000 $
#39580800
0"
0&
#39583500
b1010100 !
b1010100 %
b10011100111101010 $
#40622400
1"
1&
b10 9
b11 9
b100 9
b101 9
b110 9
b111 9
b1000 9
b1001 9
b1010100 1
b1010 2
b1111111 3
b11101000 4
b1111010 5
b1101010 6
b10101100 7
b0 8
b11001111011010011 $
#41664000
0"
0&
#41666800
b11111111 !
b11111111 %
b11101011110011010 $
#42705600
1"
1&
b10 9
b11 9
b100 9
b101 9
b110 9
b111 9
b1000 9
b1001 9
b11111111 1
b1010100 2
b1010 3
b1111111 4
b11101000 5
b1111010 6
b1101010 7
b10101100 8
b11100011001011101 $
#43747200
0"
0&
#43750200
b11111010 !
b11111010 %
b11100010010110100 $
#44788800
1"
1&
b10 9
b11 9
b100 9
b101 9
b110 9
b111 9
b1000 9
b1001 9
b11111010 1
b11111111 2
b1010100 3
b1010 4
b1111111 5
b11101000 6
b1111010 7
b1101010 8
b10011010000010011 $
#45830400
0"
0&
#45833500
b0 !
b0 %
b1110000100010001 $
#46872000
1"
1&
b10 9
b11 9
b100 9
b101 9
b110 9
b111 9
b1000 9
b1001 9
b0 1
b11111010 2
b11111111 3
b1010100 4
b1010 5
b1111111 6
b11101000 7
b1111010 8
b10001010110001101 $
#47913600
0"
0&
#47916900
b11111010 !
b11111010 %
b10110100010001111 $
#48955200
1"
1&
b10 9
b11 9
b100 9
b101 9
b110 9
b111 9
b1000 9
b1001 9
b11111010 1
b0 2
b11111010 3
b11111111 4
b1010100 5
b1010 6
b1111111 7
b11101000 8
b100111100101110100 $
#49996800
0"
0&
#50000200
b11111111 !
b11111111 %
b100111101100011101 $
#51038400
1"
1&
b10 9
b11 9
b100 9
b101 9
b110 9
b111 9
b1000 9
b1001 9
b11111111 1
b11111010 2
b0 3
b11111010 4
b11111111 5
b1010100 6
b1010 7
b1111111 8
b100001100001010100 $
#52080000
0"
0&
#52083600
b1010100 !
b1010100 %
b11101111110001101 $
#53121600
1"
1&
b10 9
b11 9
b100 9
b101 9
b110 9
b111 9
b1000 9
b1001 9
b1010100 1
b11111111 2
b11111010 3
b0 4
b11111010 5
b11111111 6
b1010100 7
b1010 8
b1110110101011010 $
#54163200
0"
0&
#54166900
b1010 !
b1010 %
b1101010011001000 $
#55204800
1"
1&
b10 9
b11 9
b100 9
b101 9
b110 9
b111 9
b1000 9
b1001 9
b1010 1
b1010100 2
b11111111 3
b11111010 4
b0 5
b11111010 6
b11111111 7
b1010100 8
b11011100010110100 $
#56246400
0"
0&
#56250300
b1111111 !
b1111111 %
b11101111110001101 $
#57288000
1"
1&
b10 9
b11 9
b100 9
b101 9
b110 9
b111 9
b1000 9
b1001 9
b1111111 1
b1010 2
b1010100 3
b11111111 4
b11111010 5
b0 6
b11111010 7
b11111111 8
b100101100001000000 $
#58329600
0"
0&
#58333600
b11101000 !
b11101000 %
b100111101100011101 $
#59371200
1"
1&
b10 9
b11 9
b100 9
b101 9
b110 9
b111 9
b1000 9
b1001 9
b11101000 1
b1111111 2
b1010 3
b1010100 4
b11111111 5
b11111010 6
b0 7
b11111010 8
b11000110100010101 $
#60412800
0"
0&
#60417000
b1111010 !
b1111010 %
b10110100010001111 $
#61454400
1"
1&
b10 9
b11 9
b100 9
b101 9
b110 9
b111 9
b1000 9
b1001 9
b1111010 1
b11101000 2
b1111111 3
b1010 4
b1010100 5
b11111111 6
b11111010 7
b0 8
b1110011001100001 $
#62496000
0"
0&
#62500300
b1101010 !
b1101010 %
b1110000100010001 $
#63537600
1"
1&
b10 9
b11 9
b100 9
b101 9
b110 9
b111 9
b1000 9
b1001 9
b1101010 1
b1111010 2
b11101000 3
b1111111 4
b1010 5
b1010100 6
b11111111 7
b11111010 8
b11010111011001010 $
#64579200
0"
0&
#64583700
b10101100 !
b10101100 %
b11100010010110100 $
#65620800
1"
1&
b10 9
b11 9
b100 9
b101 9
b110 9
b111 9
b1000 9
b1001 9
b10101100 1
b1101010 2
b1111010 3
b11101000 4
b1111111 5
b1010 6
b1010100 7
b11111111 8
b100001000010110110 $
#66662400
0"
0&
#66667000
b0 !
b0 %
b11101011110011010 $
#67704000
1"
1&
b10 9
b11 9
b100 9
b101 9
b110 9
b111 9
b1000 9
b1001 9
b0 1
b10101100 2
b1101010 3
b1111010 4
b11101000 5
b1111111 6
b1010 7
b1010100 8
b10000000011001110 $
#68745600
0"
0&
#68750400
b10101100 !
b10101100 %
b10011100111101010 $
#69787200
1"
1&
b10 9
b11 9
b100 9
b101 9
b110 9
b111 9
b1000 9
b1001 9
b10101100 1
b0 2
b10101100 3
b1101010 4
b1111010 5
b11101000 6
b1111111 7
b1010 8
b10101110100000011 $
#70828800
0"
0&
#70833700
b1101010 !
b1101010 %
b10100011100011001 $
#71870400
1"
1&
b10 9
b11 9
b100 9
b101 9
b110 9
b111 9
b1000 9
b1001 9
b1101010 1
b10101100 2
b0 3
b10101100 4
b1101010 5
b1111010 6
b11101000 7
b1111111 8
b11000000110110101 $
#72912000
0"
0&
#72917100
b1111010 !
b1111010 %
b11000011100000101 $
#73953600
1"
1&
b10 9
b11 9
b100 9
b101 9
b110 9
b111 9
b1000 9
b1001 9
b1111010 1
b1101010 2
b10101100 3
b0 4
b10101100 5
b1101010 6
b1111010 7
b11101000 8
b10010101011111110 $
#74995200
0"
0&
#75000400
b11101000 !
b11101000 %
b10100111110000100 $
#76036800
1"
1&
b10 9
b11 9
b100 9
b101 9
b110 9
b111 9
b1000 9
b1001 9
b11101000 1
b1111010 2
b1101010 3
b10101100 4
b0 5
b10101100 6
b1101010 7
b1111010 8
b11010100111100010 $
#77078400
0"
0&
#77083800
b1111111 !
b1111111 %
b11000011100000101 $
#78120000
1"
1&
b10 9
b11 9
b100 9
b101 9
b110 9
b111 9
b1000 9
b1001 9
b1111111 1
b11101000 2
b1111010 3
b1101010 4
b10101100 5
b0 6
b10101100 7
b1101010 8
b10110110111110010 $
#79161600
0"
0&
#79167100
b1010 !
b1010 %
b10100011100011001 $
#80203200
1"
1&
b10 9
b11 9
b100 9
b101 9
b110 9
b111 9
b1000 9
b1001 9
b1010 1
b1111111 2
b11101000 3
b1111010 4
b1101010 5
b10101100 6
b0 7
b10101100 8
b10010000101011000 $
#81244800
0"
0&
#81250500
b1010100 !
b1010100 %
b10011100111101010 $
#82286400
1"
1&
b10 9
b11 9
b100 9
b101 9
b110 9
b111 9
b1000 9
b1001 9
b1010100 1
b1010 2
b1111111 3
b11101000 4
b1111010 5
b1101010 6
b10101100 7
b0 8
b11001111011010011 $
#83328000
0"
0&
#83333800
b11111111 !
b11111111 %
b11101011110011010 $
#84369600
1"
1&
b10 9
b11 9
b100 9
b101 9
b110 9
b111 9
b1000 9
b1001 9
b11111111 1
b1010100 2
b1010 3
b1111111 4
b11101000 5
b1111010 6
b1101010 7
b10101100 8
b11100011001011101 $
#85411200
0"
0&
#85417200
b11111010 !
b11111010 %
b11100010010110100 $
#86452800
1"
1&
b10 9
b11 9
b100 9
b101 9
b110 9
b111 9
b1000 9
b1001 9
b11111010 1
b11111111 2
b1010100 3
b1010 4
b1111111 5
b11101000 6
b1111010 7
b1101010 8
b10011010000010011 $
#87494400
0"
0&
#87500500
b0 !
b0 %
b1110000100010001 $
#88536000
1"
1&
b10 9
b11 9
b100 9
b101 9
b110 9
b111 9
b1000 9
b1001 9
b0 1
b11111010 2
b11111111 3
b1010100 4
b1010 5
b1111111 6
b11101000 7
b1111010 8
b10001010110001101 $
#89577600
0"
0&
#89583900
b11111010 !
b11111010 %
b10110100010001111 $
#90619200
1"
1&
b10 9
b11 9
b100 9
b101 9
b110 9
b111 9
b1000 9
b1001 9
b11111010 1
b0 2
b11111010 3
b11111111 4
b1010100 5
b1010 6
b1111111 7
b11101000 8
b100111100101110100 $
#91660800
0"
0&
#91667200
b11111111 !
b11111111 %
b100111101100011101 $
#92702400
1"
1&
b10 9
b11 9
b100 9
b101 9
b110 9
b111 9
b1000 9
b1001 9
b11111111 1
b11111010 2
b0 3
b11111010 4
b11111111 5
b1010100 6
b1010 7
b1111111 8
b100001100001010100 $
#93744000
0"
0&
#93750600
b1010100 !
b1010100 %
b11101111110001101 $
#94785600
1"
1&
b10 9
b11 9
b100 9
b101 9
b110 9
b111 9
b1000 9
b1001 9
b1010100 1
b11111111 2
b11111010 3
b0 4
b11111010 5
b11111111 6
b1010100 7
b1010 8
b1110110101011010 $
#95827200
0"
0&
#95833900
b1010 !
b1010 %
b1101010011001000 $
#96868800
1"
1&
b10 9
b11 9
b100 9
b101 9
b110 9
b111 9
b1000 9
b1001 9
b1010 1
b1010100 2
b11111111 3
b11111010 4
b0 5
b11111010 6
b11111111 7
b1010100 8
b11011100010110100 $
#97910400
0"
0&
#97917300
b1111111 !
b1111111 %
b11101111110001101 $
#98952000
1"
1&
b10 9
b11 9
b100 9
b101 9
b110 9
b111 9
b1000 9
b1001 9
b1111111 1
b1010 2
b1010100 3
b11111111 4
b11111010 5
b0 6
b11111010 7
b11111111 8
b100101100001000000 $
#99993600
0"
0&
#100000600
b11101000 !
b11101000 %
b100111101100011101 $
#101035200
1"
1&
b10 9
b11 9
b100 9
b101 9
b110 9
b111 9
b1000 9
b1001 9
b11101000 1
b1111111 2
b1010 3
b1010100 4
b11111111 5
b11111010 6
b0 7
b11111010 8
b11000110100010101 $
#102076800
0"
0&
#102084000
b1111010 !
b1111010 %
b10110100010001111 $
#103118400
1"
1&
b10 9
b11 9
b100 9
b101 9
b110 9
b111 9
b1000 9
b1001 9
b1111010 1
b11101000 2
b1111111 3
b1010 4
b1010100 5
b11111111 6
b11111010 7
b0 8
b1110011001100001 $
#104160000
0"
0&
#104167300
b1101010 !
b1101010 %
b1110000100010001 $
#105201600
1"
1&
b10 9
b11 9
b100 9
b101 9
b110 9
b111 9
b1000 9
b1001 9
b1101010 1
b1111010 2
b11101000 3
b1111111 4
b1010 5
b1010100 6
b11111111 7
b11111010 8
b11010111011001010 $
#106243200
0"
0&
#106250700
b10101100 !
b10101100 %
b11100010010110100 $
#107284800
1"
1&
b10 9
b11 9
b100 9
b101 9
b110 9
b111 9
b1000 9
b1001 9
b10101100 1
b1101010 2
b1111010 3
b11101000 4
b1111111 5
b1010 6
b1010100 7
b11111111 8
b100001000010110110 $
#108326400
0"
0&
#108334000
b0 !
b0 %
b11101011110011010 $
#109368000
1"
1&
b10 9
b11 9
b100 9
b101 9
b110 9
b111 9
b1000 9
b1001 9
b0 1
b10101100 2
b1101010 3
b1111010 4
b11101000 5
b1111111 6
b1010 7
b1010100 8
b10000000011001110 $
#110409600
0"
0&
#110417400
b10101100 !
b10101100 %
b10011100111101010 $
#111451200
1"
1&
b10 9
b11 9
b100 9
b101 9
b110 9
b111 9
b1000 9
b1001 9
b10101100 1
b0 2
b10101100 3
b1101010 4
b1111010 5
b11101000 6
b1111111 7
b1010 8
b10101110100000011 $
#112492800
0"
0&
#112500700
b1101010 !
b1101010 %
b10100011100011001 $
#113534400
1"
1&
b10 9
b11 9
b100 9
b101 9
b110 9
b111 9
b1000 9
b1001 9
b1101010 1
b10101100 2
b0 3
b10101100 4
b1101010 5
b1111010 6
b11101000 7
b1111111 8
b11000000110110101 $
#114576000
0"
0&
#114584100
b1111010 !
b1111010 %
b11000011100000101 $
#115617600
1"
1&
b10 9
b11 9
b100 9
b101 9
b110 9
b111 9
b1000 9
b1001 9
b1111010 1
b1101010 2
b10101100 3
b0 4
b10101100 5
b1101010 6
b1111010 7
b11101000 8
b10010101011111110 $
#116659200
0"
0&
#116667400
b11101000 !
b11101000 %
b10100111110000100 $
#117700800
1"
1&
b10 9
b11 9
b100 9
b101 9
b110 9
b111 9
b1000 9
b1001 9
b11101000 1
b1111010 2
b1101010 3
b10101100 4
b0 5
b10101100 6
b1101010 7
b1111010 8
b11010100111100010 $
#118742400
0"
0&
#118750800
b1111111 !
b1111111 %
b11000011100000101 $
#119784000
1"
1&
b10 9
b11 9
b100 9
b101 9
b110 9
b111 9
b1000 9
b1001 9
b1111111 1
b11101000 2
b1111010 3
b1101010 4
b10101100 5
b0 6
b10101100 7
b1101010 8
b10110110111110010 $
#120825600
0"
0&
#120834100
b1010 !
b1010 %
b10100011100011001 $
#121867200
1"
1&
b10 9
b11 9
b100 9
b101 9
b110 9
b111 9
b1000 9
b1001 9
b1010 1
b1111111 2
b11101000 3
b1111010 4
b1101010 5
b10101100 6
b0 7
b10101100 8
b10010000101011000 $
#122908800
0"
0&
#122917500
b1010100 !
b1010100 %
b10011100111101010 $
#123950400
1"
1&
b10 9
b11 9
b100 9
b101 9
b110 9
b111 9
b1000 9
b1001 9
b1010100 1
b1010 2
b1111111 3
b11101000 4
b1111010 5
b1101010 6
b10101100 7
b0 8
b11001111011010011 $
#124992000
0"
0&
#125000800
b11111111 !
b11111111 %
b11101011110011010 $
#126033600
1"
1&
b10 9
b11 9
b100 9
b101 9
b110 9
b111 9
b1000 9
b1001 9
b11111111 1
b1010100 2
b1010 3
b1111111 4
b11101000 5
b1111010 6
b1101010 7
b10101100 8
b11100011001011101 $
#127075200
0"
0&
#127084200
b11111010 !
b11111010 %
b11100010010110100 $
#128116800
1"
1&
b10 9
b11 9
b100 9
b101 9
b110 9
b111 9
b1000 9
b1001 9
b11111010 1
b11111111 2
b1010100 3
b1010 4
b1111111 5
b11101000 6
b1111010 7
b1101010 8
b10011010000010011 $
#129158400
0"
0&
#129167500
b0 !
b0 %
b1110000100010001 $
#130200000
1"
1&
b10 9
b11 9
b100 9
b101 9
b110 9
b111 9
b1000 9
b1001 9
b0 1
b11111010 2
b11111111 3
b1010100 4
b1010 5
b1111111 6
b11101000 7
b1111010 8
b10001010110001101 $
#131241600
0"
0&
#131250900
b11111010 !
b11111010 %
b10110100010001111 $
#132283200
1"
1&
b10 9
b11 9
b100 9
b101 9
b110 9
b111 9
b1000 9
b1001 9
b11111010 1
b0 2
b11111010 3
b11111111 4
b1010100 5
b1010 6
b1111111 7
b11101000 8
b100111100101110100 $
#133324800
0"
0&
#133334200
b11111111 !
b11111111 %
b100111101100011101 $
#134366400
1"
1&
b10 9
b11 9
b100 9
b101 9
b110 9
b111 9
b1000 9
b1001 9
b11111111 1
b11111010 2
b0 3
b11111010 4
b11111111 5
b1010100 6
b1010 7
b1111111 8
b100001100001010100 $
#135408000
0"
0&
#135417600
b1010100 !
b1010100 %
b11101111110001101 $
#136449600
1"
1&
b10 9
b11 9
b100 9
b101 9
b110 9
b111 9
b1000 9
b1001 9
b1010100 1
b11111111 2
b11111010 3
b0 4
b11111010 5
b11111111 6
b1010100 7
b1010 8
b1110110101011010 $
#137491200
0"
0&
#137500900
b1010 !
b1010 %
b1101010011001000 $
#138532800
1"
1&
b10 9
b11 9
b100 9
b101 9
b110 9
b111 9
b1000 9
b1001 9
b1010 1
b1010100 2
b11111111 3
b11111010 4
b0 5
b11111010 6
b11111111 7
b1010100 8
b11011100010110100 $
#139574400
0"
0&
#139584300
b1111111 !
b1111111 %
b11101111110001101 $
#140616000
1"
1&
b10 9
b11 9
b100 9
b101 9
b110 9
b111 9
b1000 9
b1001 9
b1111111 1
b1010 2
b1010100 3
b11111111 4
b11111010 5
b0 6
b11111010 7
b11111111 8
b100101100001000000 $
#141657600
0"
0&
#141667600
b11101000 !
b11101000 %
b100111101100011101 $
#142699200
1"
1&
b10 9
b11 9
b100 9
b101 9
b110 9
b111 9
b1000 9
b1001 9
b11101000 1
b1111111 2
b1010 3
b1010100 4
b11111111 5
b11111010 6
b0 7
b11111010 8
b11000110100010101 $
#143740800
0"
0&
#143751000
b1111010 !
b1111010 %
b10110100010001111 $
#144782400
1"
1&
b10 9
b11 9
b100 9
b101 9
b110 9
b111 9
b1000 9
b1001 9
b1111010 1
b11101000 2
b1111111 3
b1010 4
b1010100 5
b11111111 6
b11111010 7
b0 8
b1110011001100001 $
#145824000
0"
0&
#145834300
b1101010 !
b1101010 %
b1110000100010001 $
#146865600
1"
1&
b10 9
b11 9
b100 9
b101 9
b110 9
b111 9
b1000 9
b1001 9
b1101010 1
b1111010 2
b11101000 3
b1111111 4
b1010 5
b1010100 6
b11111111 7
b11111010 8
b11010111011001010 $
#147907200
0"
0&
#147917700
b10101100 !
b10101100 %
b11100010010110100 $
#148948800
1"
1&
b10 9
b11 9
b100 9
b101 9
b110 9
b111 9
b1000 9
b1001 9
b10101100 1
b1101010 2
b1111010 3
b11101000 4
b1111111 5
b1010 6
b1010100 7
b11111111 8
b100001000010110110 $
#149990400
0"
0&
#150001000
b0 !
b0 %
b11101011110011010 $
#151032000
1"
1&
b10 9
b11 9
b100 9
b101 9
b110 9
b111 9
b1000 9
b1001 9
b0 1
b10101100 2
b1101010 3
b1111010 4
b11101000 5
b1111111 6
b1010 7
b1010100 8
b10000000011001110 $
#152073600
0"
0&
#152084400
b10101100 !
b10101100 %
b10011100111101010 $
#153115200
1"
1&
b10 9
b11 9
b100 9
b101 9
b110 9
b111 9
b1000 9
b1001 9
b10101100 1
b0 2
b10101100 3
b1101010 4
b1111010 5
b11101000 6
b1111111 7
b1010 8
b10101110100000011 $
#154156800
0"
0&
#154167700
b1101010 !
b1101010 %
b10100011100011001 $
#155198400
1"
1&
b10 9
b11 9
b100 9
b101 9
b110 9
b111 9
b1000 9
b1001 9
b1101010 1
b10101100 2
b0 3
b10101100 4
b1101010 5
b1111010 6
b11101000 7
b1111111 8
b11000000110110101 $
#156240000
0"
0&
#156251100
b1111010 !
b1111010 %
b11000011100000101 $
#157281600
1"
1&
b10 9
b11 9
b100 9
b101 9
b110 9
b111 9
b1000 9
b1001 9
b1111010 1
b1101010 2
b10101100 3
b0 4
b10101100 5
b1101010 6
b1111010 7
b11101000 8
b10010101011111110 $
#158323200
0"
0&
#158334400
b11101000 !
b11101000 %
b10100111110000100 $
#159364800
1"
1&
b10 9
b11 9
b100 9
b101 9
b110 9
b111 9
b1000 9
b1001 9
b11101000 1
b1111010 2
b1101010 3
b10101100 4
b0 5
b10101100 6
b1101010 7
b1111010 8
b11010100111100010 $
#160406400
0"
0&
#160417800
b1111111 !
b1111111 %
b11000011100000101 $
#161448000
1"
1&
b10 9
b11 9
b100 9
b101 9
b110 9
b111 9
b1000 9
b1001 9
b1111111 1
b11101000 2
b1111010 3
b1101010 4
b10101100 5
b0 6
b10101100 7
b1101010 8
b10110110111110010 $
#162489600
0"
0&
