iir/iir_eda_sim_files/design.sv

module Chevychev_highpass (
    data_in, data_out, clk, rst
);

  output[63:0] data_out;
input[7:0] data_in;
input clk, rst;

parameter b0 = 8'b10000001;
parameter b1 = 8'b01110110;
parameter b2 = 8'b10100100;
parameter b3 = 8'b00101011;
parameter b4 = 8'b11111111;
parameter b5 = 8'b00000000;
parameter b6 = 8'b11010100;
parameter b7 = 8'b01011011;
parameter b8 = 8'b10001001;
parameter b9 = 8'b01111110;


parameter a1 = 8'b00000000;
parameter a2 = 8'b11111111;
parameter a3 = 8'b00010010;
parameter a4 = 8'b10111110;
parameter a5 = 8'b01011101;
parameter a6 = 8'b01110011;
parameter a7 = 8'b01100100;
parameter a8 = 8'b01010101;
parameter a9 = 8'b01010101;


wire[63:0] data_feedforward;
wire[63:0] data_feedback;

reg[63:0] ff_data[1:9];
reg[63:0] fb_data[1:9];

assign data_feedforward = b0*data_in+b1*ff_data[1]+b2*ff_data[2]+b3*ff_data[3]+b4*ff_data[4]+b5*ff_data[5]+b6*ff_data[6]+b7*ff_data[7]+b8*ff_data[8]+b9*ff_data[9];
assign data_feedback = a1*fb_data[1]+a2*fb_data[2]+a3*fb_data[3]+a4*fb_data[4]+a5*fb_data[5]+a6*fb_data[6]+a7*fb_data[7]+a8*fb_data[8]+a9*fb_data[9];

assign data_out = (data_feedforward - data_feedback);

integer k;
always @ (posedge clk)
    if (rst==1)
    begin
        for (k=1;k<=9;k=k+1)
        begin
            ff_data[k]<=0;
            fb_data[k]<=0;
        end
    end

    else
    begin
      	ff_data[1]<=data_in;
      	fb_data[1]<=data_out;
        for (k=2;k<=9;k=k+1)
        begin
            ff_data[k]<=ff_data[k-1];
            fb_data[k]<=fb_data[k-1];
        end
    end

endmodule

iir/iir_eda_sim_files/testbench.sv
`timescale 1ns/10ps
module filter_testbench;

	reg[7:0] data_in;
	reg clk, rst;
  	wire[63:0] data_out;


    Chevychev_highpass filter1(  //Chevychev_highpass instead of fir_filter for iir
        .data_in(data_in), 
        .data_out(data_out), 
        .clk(clk), 
        .rst(rst)
    );
    

    initial 
        begin
           clk = 1'b0;
	   forever 
            begin
                #10416 clk = ~clk;
                if (clk == 1)
                  begin
                  	$display(data_out);
                  end
            end  
        end

	initial
	begin
        #0      rst=1;
                data_in=8'b00000000;
        #20832  rst=0;
        #20833  data_in=8'b00000000;
        #20834  data_in=8'b11111010;
        #20833  data_in=8'b11111111;
        #20834  data_in=8'b01010100;
        #20833  data_in=8'b00001010;
        #20834  data_in=8'b01111111;
        #20833  data_in=8'b11101000;
        #20834  data_in=8'b01111010;
        #20833  data_in=8'b01101010;
        #20834  data_in=8'b10101100;
        #20833  data_in=8'b00000000;
        #20834  data_in=8'b10101100;
        #20833  data_in=8'b01101010;
        #20834  data_in=8'b01111010;
        #20833  data_in=8'b11101000;
        #20834  data_in=8'b01111111;
        #20833  data_in=8'b00001010;
        #20834  data_in=8'b01010100;
        #20833  data_in=8'b11111111;
        #20834  data_in=8'b11111010;
        #20833  data_in=8'b00000000;
        #20834  data_in=8'b11111010;
        #20833  data_in=8'b11111111;
        #20834  data_in=8'b01010100;
        #20833  data_in=8'b00001010;
        #20834  data_in=8'b01111111;
        #20833  data_in=8'b11101000;
        #20834  data_in=8'b01111010;
        #20833  data_in=8'b01101010;
        #20834  data_in=8'b10101100;
        #20833  data_in=8'b00000000;
        #20834  data_in=8'b10101100;
        #20833  data_in=8'b01101010;
        #20834  data_in=8'b01111010;
        #20833  data_in=8'b11101000;
        #20834  data_in=8'b01111111;
        #20833  data_in=8'b00001010;
        #20834  data_in=8'b01010100;
        #20833  data_in=8'b11111111;
        #20834  data_in=8'b11111010;
        #20833  data_in=8'b00000000;
        #20834  data_in=8'b11111010;
        #20833  data_in=8'b11111111;
        #20834  data_in=8'b01010100;
        #20833  data_in=8'b00001010;
        #20834  data_in=8'b01111111;
        #20833  data_in=8'b11101000;
        #20834  data_in=8'b01111010;
        #20833  data_in=8'b01101010;
        #20834  data_in=8'b10101100;
        #20833  data_in=8'b00000000;
        #20834  data_in=8'b10101100;
        #20833  data_in=8'b01101010;
        #20834  data_in=8'b01111010;
        #20833  data_in=8'b11101000;
        #20834  data_in=8'b01111111;
        #20833  data_in=8'b00001010;
        #20834  data_in=8'b01010100;
        #20833  data_in=8'b11111111;
        #20834  data_in=8'b11111010;
        #20833  data_in=8'b00000000;
        #20834  data_in=8'b11111010;
        #20833  data_in=8'b11111111;
        #20834  data_in=8'b01010100;
        #20833  data_in=8'b00001010;
        #20834  data_in=8'b01111111;
        #20833  data_in=8'b11101000;
        #20834  data_in=8'b01111010;
        #20833  data_in=8'b01101010;
        #20834  data_in=8'b10101100;
        #20833  data_in=8'b00000000;
        #20834  data_in=8'b10101100;
        #20833  data_in=8'b01101010;
        #20834  data_in=8'b01111010;
        #20833  data_in=8'b11101000;
        #20834  data_in=8'b01111111;
        #20833  data_in=8'b00001010;
        #20834  data_in=8'b01010100;
        #20833  data_in=8'b11111111;
        #20834  data_in=8'b11111010;
        #20833  data_in=8'b00000000;
        #20834  data_in=8'b11111010;
        #20833  data_in=8'b11111111;
        #20834  data_in=8'b01010100;
        #20833  data_in=8'b00001010;
        #20834  data_in=8'b01111111;
        #20833  data_in=8'b11101000;
        #20834  data_in=8'b01111010;
        #20833  data_in=8'b01101010;
        #20834  data_in=8'b10101100;
        #20833  data_in=8'b00000000;
        #20834  data_in=8'b10101100;
        #20833  data_in=8'b01101010;
        #20834  data_in=8'b01111010;
        #20833  data_in=8'b11101000;
        #20834  data_in=8'b01111111;
	    #20832  $stop;
	end

	initial 
	begin
		$dumpfile("filter_dump.vcd");
		$dumpvars;
	end
endmodule

iir/iir_eda_sim_files/filter_dump.vcd
$date
    Mar  6, 2023  07:44:01
$end
$version
    TOOL:	xmsim	20.09-s003
$end
$timescale
    10 ps
$end

$scope module filter_testbench $end
$var reg       8 !    data_in [7:0] $end
$var reg       1 "    clk $end
$var reg       1 #    rst $end
$var wire     64 $    data_out [63:0] $end

$scope module filter1 $end
$var wire     64 $    data_out [63:0] $end
$var wire      8 %    data_in [7:0] $end
$var wire      1 &    clk  $end
$var wire      1 '    rst  $end
$var parameter  8 (    b0 $end
$var parameter  8 )    b1 $end
$var parameter  8 *    b2 $end
$var parameter  8 +    b3 $end
$var parameter  8 ,    b4 $end
$var parameter  8 -    b5 $end
$var parameter  8 .    b6 $end
$var parameter  8 /    b7 $end
$var parameter  8 0    b8 $end
$var parameter  8 1    b9 $end
$var parameter  8 2    a1 $end
$var parameter  8 3    a2 $end
$var parameter  8 4    a3 $end
$var parameter  8 5    a4 $end
$var parameter  8 6    a5 $end
$var parameter  8 7    a6 $end
$var parameter  8 8    a7 $end
$var parameter  8 9    a8 $end
$var parameter  8 :    a9 $end
$var wire     64 ;    data_feedforward [63:0] $end
$var wire     64 <    data_feedback [63:0] $end
$var reg      64 =    ff_data[1] [63:0] $end
$var reg      64 >    ff_data[2] [63:0] $end
$var reg      64 ?    ff_data[3] [63:0] $end
$var reg      64 @    ff_data[4] [63:0] $end
$var reg      64 A    ff_data[5] [63:0] $end
$var reg      64 B    ff_data[6] [63:0] $end
$var reg      64 C    ff_data[7] [63:0] $end
$var reg      64 D    ff_data[8] [63:0] $end
$var reg      64 E    ff_data[9] [63:0] $end
$var reg      64 F    fb_data[1] [63:0] $end
$var reg      64 G    fb_data[2] [63:0] $end
$var reg      64 H    fb_data[3] [63:0] $end
$var reg      64 I    fb_data[4] [63:0] $end
$var reg      64 J    fb_data[5] [63:0] $end
$var reg      64 K    fb_data[6] [63:0] $end
$var reg      64 L    fb_data[7] [63:0] $end
$var reg      64 M    fb_data[8] [63:0] $end
$var reg      64 N    fb_data[9] [63:0] $end
$var integer  32 O    k $end
$upscope $end

$upscope $end

$enddefinitions $end
$dumpvars
b1010101 :
b1010101 9
b1100100 8
b1110011 7
b1011101 6
b10111110 5
b10010 4
b11111111 3
b0 2
b1111110 1
b10001001 0
b1011011 /
b11010100 .
b0 -
b11111111 ,
b101011 +
b10100100 *
b1110110 )
b10000001 (
b0 !
0"
1#
bx $
b0 %
0&
1'
bx ;
bx <
bx =
bx >
bx ?
bx @
bx A
bx B
bx C
bx D
bx E
bx F
bx G
bx H
bx I
bx J
bx K
bx L
bx M
bx N
bx O
$end
#1041600
1"
1&
b1 O
b10 O
b11 O
b100 O
b101 O
b110 O
b111 O
b1000 O
b1001 O
b1010 O
b0 =
b0 F
b0 >
b0 G
b0 ?
b0 H
b0 @
b0 I
b0 A
b0 J
b0 B
b0 K
b0 C
b0 L
b0 D
b0 M
b0 E
b0 N
b0 <
b0 ;
b0 $
#2083200
0#
0"
0&
0'
#3124800
1"
1&
b10 O
b11 O
b100 O
b101 O
b110 O
b111 O
b1000 O
b1001 O
b1010 O
#4166400
0"
0&
#5208000
1"
1&
#6249600
0"
0&
#6249900
b11111010 !
b11111010 %
b111110111111010 ;
b111110111111010 $
#7291200
1"
1&
b10 O
b11 O
b100 O
b101 O
b110 O
b111 O
b1000 O
b1001 O
b1010 O
b11111010 =
b111110111111010 F
b1111000100110110 ;
b1111000100110110 $
#8332800
0"
0&
#8333200
b11111111 !
b11111111 %
b1111001110111011 ;
b1111001110111011 $
#9374400
1"
1&
b10 O
b11 O
b100 O
b101 O
b110 O
b111 O
b1000 O
b1001 O
b1010 O
b11111111 =
b1111001110111011 F
b11111010 >
b111110111111010 G
b11111010111110000000110 <
b11001011000110001 ;
b1111111111111111111111111111111111111111100001000001101000101011 $
#10416000
0"
0&
#10416600
b1010100 !
b1010100 %
b10100000000000110 ;
b1111111111111111111111111111111111111111100000111100010000000000 $
#11457600
1"
1&
b10 O
b11 O
b100 O
b101 O
b110 O
b111 O
b1000 O
b1001 O
b1010 O
b1010100 =
b1111111111111111111111111111111111111111100000111100010000000000 F
b11111111 >
b1111001110111011 G
b11111010 ?
b111110111111010 H
b111110111010001011011001 <
b10001111001100110 ;
b1111111111111111111111111111111111111111000001010111101110001101 $
#12499200
0"
0&
#12499900
b1010 !
b1010 %
b1111100100011100 ;
b1111111111111111111111111111111111111111000001010101011001000011 $
#13540800
1"
1&
b10 O
b11 O
b100 O
b101 O
b110 O
b111 O
b1000 O
b1001 O
b1010 O
b1010 =
b1111111111111111111111111111111111111111000001010101011001000011 F
b1010100 >
b1111111111111111111111111111111111111111100000111100010000000000 G
b11111111 ?
b1111001110111011 H
b11111010 @
b111110111111010 I
b1111111111111111111111111111111110000100101011101101111010110010 <
b10110001101010001 ;
b1111011010100101000010010011111 $
#14582400
0"
0&
#14583300
b1111111 !
b1111111 %
b11001111001000110 ;
b1111011010100101011111110010100 $
#15624000
1"
1&
b10 O
b11 O
b100 O
b101 O
b110 O
b111 O
b1000 O
b1001 O
b1010 O
b1111111 =
b1111011010100101011111110010100 F
b1010 >
b1111111111111111111111111111111111111111000001010101011001000011 G
b1010100 ?
b1111111111111111111111111111111111111111100000111100010000000000 H
b11111111 @
b1111001110111011 I
b11111010 A
b111110111111010 J
b1111111111111111111111111111111011111110011101110101110101011001 <
b11000110100001110 ;
b100000001100010100010111110110101 $
#16665600
0"
0&
#16666600
b11101000 !
b11101000 %
b11100000111110111 ;
b100000001100010100110010010011110 $
#17707200
1"
1&
b10 O
b11 O
b100 O
b101 O
b110 O
b111 O
b1000 O
b1001 O
b1010 O
b11101000 =
b100000001100010100110010010011110 F
b1111111 >
b1111011010100101011111110010100 G
b1010 ?
b1111111111111111111111111111111111111111000001010101011001000011 H
b1010100 @
b1111111111111111111111111111111111111111100000111100010000000000 I
b11111111 A
b1111001110111011 J
b11111010 B
b111110111111010 K
b111101001101010001010010111111101011111 <
b100101010110010110 ;
b1111111111111111111111111000010110010101110110001101011000110111 $
#18748800
0"
0&
#18750000
b1111010 !
b1111010 %
b100001111000101000 ;
b1111111111111111111111111000010110010101110110001001111011001001 $
#19790400
1"
1&
b10 O
b11 O
b100 O
b101 O
b110 O
b111 O
b1000 O
b1001 O
b1010 O
b1111010 =
b1111111111111111111111111000010110010101110110001001111011001001 F
b11101000 >
b100000001100010100110010010011110 G
b1111111 ?
b1111011010100101011111110010100 H
b1010 @
b1111111111111111111111111111111111111111000001010101011001000011 I
b1010100 A
b1111111111111111111111111111111111111111100000111100010000000000 J
b11111111 B
b1111001110111011 K
b11111010 C
b111110111111010 L
b10000100001001110000111101001111000101101 <
b100101010110101011 ;
b1111111111111111111111101111011110110001111000111011011101111110 $
#20832000
0"
0&
#20833300
b1101010 !
b1101010 %
b100100110110011011 ;
b1111111111111111111111101111011110110001111000111010111101101110 $
#21873600
1"
1&
b10 O
b11 O
b100 O
b101 O
b110 O
b111 O
b1000 O
b1001 O
b1010 O
b1101010 =
b1111111111111111111111101111011110110001111000111010111101101110 F
b1111010 >
b1111111111111111111111111000010110010101110110001001111011001001 G
b11101000 ?
b100000001100010100110010010011110 H
b1111111 @
b1111011010100101011111110010100 I
b1010 A
b1111111111111111111111111111111111111111000001010101011001000011 J
b1010100 B
b1111111111111111111111111111111111111111100000111100010000000000 K
b11111111 C
b1111001110111011 L
b11111010 D
b111110111111010 M
b1111111111111111100001100111110101010011100101011101100010010000 <
b100111111111100110 ;
b11110011000001010101100011011001010011101010110 $
#22915200
0"
0&
#22916700
b10101100 !
b10101100 %
b101010000100101000 ;
b11110011000001010101100011011001100100010011000 $
#23956800
1"
1&
b10 O
b11 O
b100 O
b101 O
b110 O
b111 O
b1000 O
b1001 O
b1010 O
b10101100 =
b11110011000001010101100011011001100100010011000 F
b1101010 >
b1111111111111111111111101111011110110001111000111010111101101110 G
b1111010 ?
b1111111111111111111111111000010110010101110110001001111011001001 H
b11101000 @
b100000001100010100110010010011110 I
b1111111 A
b1111011010100101011111110010100 J
b1010 B
b1111111111111111111111111111111111111111000001010101011001000011 K
b1010100 C
b1111111111111111111111111111111111111111100000111100010000000000 L
b11111111 D
b1111001110111011 M
b11111010 E
b111110111111010 N
b1111111111111110111100010000101000001100001001100011111111101110 <
b110000111100011001 ;
b1000011101111010111110011110111001100111100101011 $
#24998400
0"
0&
#25000000
b0 !
b0 %
b101011100001101101 ;
b1000011101111010111110011110111000111100001111111 $
#26040000
1"
1&
b10 O
b11 O
b100 O
b101 O
b110 O
b111 O
b1000 O
b1001 O
b1010 O
b0 =
b1000011101111010111110011110111000111100001111111 F
b10101100 >
b11110011000001010101100011011001100100010011000 G
b1101010 ?
b1111111111111111111111101111011110110001111000111010111101101110 H
b1111010 @
b1111111111111111111111111000010110010101110110001001111011001001 I
b11101000 A
b100000001100010100110010010011110 J
b1111111 B
b1111011010100101011111110010100 K
b1010 C
b1111111111111111111111111111111111111111000001010101011001000011 L
b1010100 D
b1111111111111111111111111111111111111111100000111100010000000000 M
b11111111 E
b1111001110111011 N
b1111000100111000100110111100011101111010100111001110111 <
b100001000010110100 ;
b1111111110000111011000111011001000011100010001001100001000111101 $
#27081600
0"
0&
#27083400
b10101100 !
b10101100 %
b100110011101100000 ;
b1111111110000111011000111011001000011100010001010001100011101001 $
#28123200
1"
1&
b10 O
b11 O
b100 O
b101 O
b110 O
b111 O
b1000 O
b1001 O
b1010 O
b10101100 =
b1111111110000111011000111011001000011100010001010001100011101001 F
b0 >
b1000011101111010111110011110111000111100001111111 G
b10101100 ?
b11110011000001010101100011011001100100010011000 H
b1101010 @
b1111111111111111111111101111011110110001111000111010111101101110 I
b1111010 A
b1111111111111111111111111000010110010101110110001001111011001001 J
b11101000 B
b100000001100010100110010010011110 K
b1111111 C
b1111011010100101011111110010100 L
b1010 D
b1111111111111111111111111111111111111111000001010101011001000011 M
b1010100 E
b1111111111111111111111111111111111111111100000111100010000000000 N
b100010101100000100010111011011111111100111100010011100011 <
b100100100001100101 ;
b1111111011101010011111011101000100100000000011101000001110000010 $
#29164800
0"
0&
#29166700
b1101010 !
b1101010 %
b100010011100100011 ;
b1111111011101010011111011101000100100000000011100110001001000000 $
#30206400
1"
1&
b10 O
b11 O
b100 O
b101 O
b110 O
b111 O
b1000 O
b1001 O
b1010 O
b1101010 =
b1111111011101010011111011101000100100000000011100110001001000000 F
b10101100 >
b1111111110000111011000111011001000011100010001010001100011101001 G
b0 ?
b1000011101111010111110011110111000111100001111111 H
b10101100 @
b11110011000001010101100011011001100100010011000 I
b1101010 A
b1111111111111111111111101111011110110001111000111010111101101110 J
b1111010 B
b1111111111111111111111111000010110010101110110001001111011001001 K
b11101000 C
b100000001100010100110010010011110 L
b1111111 D
b1111011010100101011111110010100 M
b1010 E
b1111111111111111111111111111111111111111000001010101011001000011 N
b1000100001001000111101000011110001110000011001011100011100110001 <
b101000000000101101 ;
b111011110110111000010111100001110001111100111001011100011111100 $
#31248000
0"
0&
#31250100
b1111010 !
b1111010 %
b101000100000111101 ;
b111011110110111000010111100001110001111100111001100000100001100 $
#32289600
1"
1&
b10 O
b11 O
b100 O
b101 O
b110 O
b111 O
b1000 O
b1001 O
b1010 O
b1111010 =
b111011110110111000010111100001110001111100111001100000100001100 F
b1101010 >
b1111111011101010011111011101000100100000000011100110001001000000 G
b10101100 ?
b1111111110000111011000111011001000011100010001010001100011101001 H
b0 @
b1000011101111010111110011110111000111100001111111 I
b10101100 A
b11110011000001010101100011011001100100010011000 J
b1101010 B
b1111111111111111111111101111011110110001111000111010111101101110 K
b1111010 C
b1111111111111111111111111000010110010101110110001001111011001001 L
b11101000 D
b100000001100010100110010010011110 M
b1111111 E
b1111011010100101011111110010100 N
b1110010000001100111011101100101001110011101010001100010100100100 <
b100001010001010010 ;
b1101111110011000100010011010110001100010110010100111100101110 $
#33331200
0"
0&
#33333400
b11101000 !
b11101000 %
b100100101111000000 ;
b1101111110011000100010011010110001100010110011000011010011100 $
#34372800
1"
1&
b10 O
b11 O
b100 O
b101 O
b110 O
b111 O
b1000 O
b1001 O
b1010 O
b11101000 =
b1101111110011000100010011010110001100010110011000011010011100 F
b1111010 >
b111011110110111000010111100001110001111100111001100000100001100 G
b1101010 ?
b1111111011101010011111011101000100100000000011100110001001000000 H
b10101100 @
b1111111110000111011000111011001000011100010001010001100011101001 I
b0 A
b1000011101111010111110011110111000111100001111111 J
b10101100 B
b11110011000001010101100011011001100100010011000 K
b1101010 C
b1111111111111111111111101111011110110001111000111010111101101110 L
b1111010 D
b1111111111111111111111111000010110010101110110001001111011001001 M
b11101000 E
b100000001100010100110010010011110 N
b1101001011100110000001000011000000010110001101100011101011111000 <
b110101001010111010 ;
b10110100011001111110111100111111101001110011010001011111000010 $
#35414400
0"
0&
#35416800
b1111111 !
b1111111 %
b110001110111010001 ;
b10110100011001111110111100111111101001110011001110001011011001 $
#36456000
1"
1&
b10 O
b11 O
b100 O
b101 O
b110 O
b111 O
b1000 O
b1001 O
b1010 O
b1111111 =
b10110100011001111110111100111111101001110011001110001011011001 F
b11101000 >
b1101111110011000100010011010110001100010110011000011010011100 G
b1111010 ?
b111011110110111000010111100001110001111100111001100000100001100 H
b1101010 @
b1111111011101010011111011101000100100000000011100110001001000000 I
b10101100 A
b1111111110000111011000111011001000011100010001010001100011101001 J
b0 B
b1000011101111010111110011110111000111100001111111 K
b10101100 C
b11110011000001010101100011011001100100010011000 L
b1101010 D
b1111111111111111111111101111011110110001111000111010111101101110 M
b1111010 E
b1111111111111111111111111000010110010101110110001001111011001001 N
b100100011011110010000000010000110101110000010000001010100010001 <
b100011111100100111 ;
b1011011100100001101111111101111001010001111110100010101000010110 $
#37497600
0"
0&
#37500100
b1010 !
b1010 %
b100000010000110010 ;
b1011011100100001101111111101111001010001111110011110111100100001 $
#38539200
1"
1&
b10 O
b11 O
b100 O
b101 O
b110 O
b111 O
b1000 O
b1001 O
b1010 O
b1010 =
b1011011100100001101111111101111001010001111110011110111100100001 F
b1111111 >
b10110100011001111110111100111111101001110011001110001011011001 G
b11101000 ?
b1101111110011000100010011010110001100010110011000011010011100 H
b1111010 @
b111011110110111000010111100001110001111100111001100000100001100 I
b1101010 A
b1111111011101010011111011101000100100000000011100110001001000000 J
b10101100 B
b1111111110000111011000111011001000011100010001010001100011101001 K
b0 C
b1000011101111010111110011110111000111100001111111 L
b10101100 D
b11110011000001010101100011011001100100010011000 M
b1101010 E
b1111111111111111111111101111011110110001111000111010111101101110 N
b10001101100111000110111011001001000010110100111000000110001100 <
b100001101000101000 ;
b1101110010011000111001000100110110111101001011101001100010011100 $
#39580800
0"
0&
#39583500
b1010100 !
b1010100 %
b100011111101110010 ;
b1101110010011000111001000100110110111101001011101011110111100110 $
#40622400
1"
1&
b10 O
b11 O
b100 O
b101 O
b110 O
b111 O
b1000 O
b1001 O
b1010 O
b1010100 =
b1101110010011000111001000100110110111101001011101011110111100110 F
b1010 >
b1011011100100001101111111101111001010001111110011110111100100001 G
b1111111 ?
b10110100011001111110111100111111101001110011001110001011011001 H
b11101000 @
b1101111110011000100010011010110001100010110011000011010011100 I
b1111010 A
b111011110110111000010111100001110001111100111001100000100001100 J
b1101010 B
b1111111011101010011111011101000100100000000011100110001001000000 K
b10101100 C
b1111111110000111011000111011001000011100010001010001100011101001 L
b0 D
b1000011101111010111110011110111000111100001111111 M
b10101100 E
b11110011000001010101100011011001100100010011000 N
b10011100010011101001010110110100011000100001111010100010101100 <
b100011110101110101 ;
b1101100011101100010110101001001011100111011110101001010011001001 $
#41664000
0"
0&
#41666800
b11111111 !
b11111111 %
b101001001110100000 ;
b1101100011101100010110101001001011100111011110101110101011110100 $
#42705600
1"
1&
b10 O
b11 O
b100 O
b101 O
b110 O
b111 O
b1000 O
b1001 O
b1010 O
b11111111 =
b1101100011101100010110101001001011100111011110101110101011110100 F
b1010100 >
b1101110010011000111001000100110110111101001011101011110111100110 G
b1010 ?
b1011011100100001101111111101111001010001111110011110111100100001 H
b1111111 @
b10110100011001111110111100111111101001110011001110001011011001 I
b11101000 A
b1101111110011000100010011010110001100010110011000011010011100 J
b1111010 B
b111011110110111000010111100001110001111100111001100000100001100 K
b1101010 C
b1111111011101010011111011101000100100000000011100110001001000000 L
b10101100 D
b1111111110000111011000111011001000011100010001010001100011101001 M
b0 E
b1000011101111010111110011110111000111100001111111 N
b111000001100010100011000010110000011011111001101001110100010010 <
b101001001011001010 ;
b1000111110011101011100111101001111100100000110111111010110111000 $
#43747200
0"
0&
#43750200
b11111010 !
b11111010 %
b101001000001000101 ;
b1000111110011101011100111101001111100100000110111111001100110011 $
#44788800
1"
1&
b10 O
b11 O
b100 O
b101 O
b110 O
b111 O
b1000 O
b1001 O
b1010 O
b11111010 =
b1000111110011101011100111101001111100100000110111111001100110011 F
b11111111 >
b1101100011101100010110101001001011100111011110101110101011110100 G
b1010100 ?
b1101110010011000111001000100110110111101001011101011110111100110 H
b1010 @
b1011011100100001101111111101111001010001111110011110111100100001 I
b1111111 A
b10110100011001111110111100111111101001110011001110001011011001 J
b11101000 B
b1101111110011000100010011010110001100010110011000011010011100 K
b1111010 C
b111011110110111000010111100001110001111100111001100000100001100 L
b1101010 D
b1111111011101010011111011101000100100000000011100110001001000000 M
b10101100 E
b1111111110000111011000111011001000011100010001010001100011101001 N
b1011000100101100010110110101100111010100110100100000101111101100 <
b110010010110000100 ;
b100111011010011101001001010011000101011001100010001100110011000 $
#45830400
0"
0&
#45833500
b0 !
b0 %
b101010011110001010 ;
b100111011010011101001001010011000101011001100001001101110011110 $
#46872000
1"
1&
b10 O
b11 O
b100 O
b101 O
b110 O
b111 O
b1000 O
b1001 O
b1010 O
b0 =
b100111011010011101001001010011000101011001100001001101110011110 F
b11111010 >
b1000111110011101011100111101001111100100000110111111001100110011 G
b11111111 ?
b1101100011101100010110101001001011100111011110101110101011110100 H
b1010100 @
b1101110010011000111001000100110110111101001011101011110111100110 I
b1010 A
b1011011100100001101111111101111001010001111110011110111100100001 J
b1111111 B
b10110100011001111110111100111111101001110011001110001011011001 K
b11101000 C
b1101111110011000100010011010110001100010110011000011010011100 L
b1111010 D
b111011110110111000010111100001110001111100111001100000100001100 M
b1101010 E
b1111111011101010011111011101000100100000000011100110001001000000 N
b10000001110010011010011000100111011100110011011100100101001101 <
b100100111111000011 ;
b1101111110001101100101100111011000100011001101001000011001110110 $
#47913600
0"
0&
#47916900
b11111010 !
b11111010 %
b101100110110111101 ;
b1101111110001101100101100111011000100011001101010000010001110000 $
#48955200
1"
1&
b10 O
b11 O
b100 O
b101 O
b110 O
b111 O
b1000 O
b1001 O
b1010 O
b11111010 =
b1101111110001101100101100111011000100011001101010000010001110000 F
b0 >
b100111011010011101001001010011000101011001100001001101110011110 G
b11111010 ?
b1000111110011101011100111101001111100100000110111111001100110011 H
b11111111 @
b1101100011101100010110101001001011100111011110101110101011110100 I
b1010100 A
b1101110010011000111001000100110110111101001011101011110111100110 J
b1010 B
b1011011100100001101111111101111001010001111110011110111100100001 K
b1111111 C
b10110100011001111110111100111111101001110011001110001011011001 L
b11101000 D
b1101111110011000100010011010110001100010110011000011010011100 M
b1111010 E
b111011110110111000010111100001110001111100111001100000100001100 N
b1010101010100100011111000111110100000110101011000100110011111101 <
b110000011011010110 ;
b101010101011011100000111000001011111001010101101011100111011001 $
#49996800
0"
0&
#50000200
b11111111 !
b11111111 %
b110000100101011011 ;
b101010101011011100000111000001011111001010101101011110001011110 $
#51038400
1"
1&
b10 O
b11 O
b100 O
b101 O
b110 O
b111 O
b1000 O
b1001 O
b1010 O
b11111111 =
b101010101011011100000111000001011111001010101101011110001011110 F
b11111010 >
b1101111110001101100101100111011000100011001101010000010001110000 G
b0 ?
b100111011010011101001001010011000101011001100001001101110011110 H
b11111010 @
b1000111110011101011100111101001111100100000110111111001100110011 I
b11111111 A
b1101100011101100010110101001001011100111011110101110101011110100 J
b1010100 B
b1101110010011000111001000100110110111101001011101011110111100110 K
b1010 C
b1011011100100001101111111101111001010001111110011110111100100001 L
b1111111 D
b10110100011001111110111100111111101001110011001110001011011001 M
b11101000 E
b1101111110011000100010011010110001100010110011000011010011100 N
b1000000011010110001001101001000110111100000000011111001000111001 <
b111000111001111100 ;
b111111100101001110110010110111001000100000000011001110001000011 $
#52080000
0"
0&
#52083600
b1010100 !
b1010100 %
b110011100001010001 ;
b111111100101001110110010110111001000100000000010100011000011000 $
#53121600
1"
1&
b10 O
b11 O
b100 O
b101 O
b110 O
b111 O
b1000 O
b1001 O
b1010 O
b1010100 =
b111111100101001110110010110111001000100000000010100011000011000 F
b11111111 >
b101010101011011100000111000001011111001010101101011110001011110 G
b11111010 ?
b1101111110001101100101100111011000100011001101010000010001110000 H
b0 @
b100111011010011101001001010011000101011001100001001101110011110 I
b11111010 A
b1000111110011101011100111101001111100100000110111111001100110011 J
b11111111 B
b1101100011101100010110101001001011100111011110101110101011110100 K
b1010100 C
b1101110010011000111001000100110110111101001011101011110111100110 L
b1010 D
b1011011100100001101111111101111001010001111110011110111100100001 M
b1111111 E
b10110100011001111110111100111111101001110011001110001011011001 N
b1101000100011111000010100100100001111110110110000011101111000011 <
b100101001101001010 ;
b10111011100000111101011011011110000001001010100001011110000111 $
#54163200
0"
0&
#54166900
b1010 !
b1010 %
b100010111000000000 ;
b10111011100000111101011011011110000001001010011111001000111101 $
#55204800
1"
1&
b10 O
b11 O
b100 O
b101 O
b110 O
b111 O
b1000 O
b1001 O
b1010 O
b1010 =
b10111011100000111101011011011110000001001010011111001000111101 F
b1010100 >
b111111100101001110110010110111001000100000000010100011000011000 G
b11111111 ?
b101010101011011100000111000001011111001010101101011110001011110 H
b11111010 @
b1101111110001101100101100111011000100011001101010000010001110000 I
b0 A
b100111011010011101001001010011000101011001100001001101110011110 J
b11111010 B
b1000111110011101011100111101001111100100000110111111001100110011 K
b11111111 C
b1101100011101100010110101001001011100111011110101110101011110100 L
b1010100 D
b1101110010011000111001000100110110111101001011101011110111100110 M
b1010 E
b1011011100100001101111111101111001010001111110011110111100100001 N
b1000011000011110001111000100101000000100011100110101111010010110 <
b101011111011011110 ;
b111100111100001110000111011010111111011100011110110000001001000 $
#56246400
0"
0&
#56250300
b1111111 !
b1111111 %
b101111100111010011 ;
b111100111100001110000111011010111111011100011111001101100111101 $
#57288000
1"
1&
b10 O
b11 O
b100 O
b101 O
b110 O
b111 O
b1000 O
b1001 O
b1010 O
b1111111 =
b111100111100001110000111011010111111011100011111001101100111101 F
b1010 >
b10111011100000111101011011011110000001001010011111001000111101 G
b1010100 ?
b111111100101001110110010110111001000100000000010100011000011000 H
b11111111 @
b101010101011011100000111000001011111001010101101011110001011110 I
b11111010 A
b1101111110001101100101100111011000100011001101010000010001110000 J
b0 B
b100111011010011101001001010011000101011001100001001101110011110 K
b11111010 C
b1000111110011101011100111101001111100100000110111111001100110011 L
b11111111 D
b1101100011101100010110101001001011100111011110101110101011110100 M
b1010100 E
b1101110010011000111001000100110110111101001011101011110111100110 N
b1111101100110011011001011010101101110111100101111001101100101111 <
b101001011110111011 ;
b10011001100100110100101010010001000011010101111110010001100 $
#58329600
0"
0&
#58333600
b11101000 !
b11101000 %
b101100110010100100 ;
b10011001100100110100101010010001000011010110011000101110101 $
#59371200
1"
1&
b10 O
b11 O
b100 O
b101 O
b110 O
b111 O
b1000 O
b1001 O
b1010 O
b11101000 =
b10011001100100110100101010010001000011010110011000101110101 F
b1111111 >
b111100111100001110000111011010111111011100011111001101100111101 G
b1010 ?
b10111011100000111101011011011110000001001010011111001000111101 H
b1010100 @
b111111100101001110110010110111001000100000000010100011000011000 I
b11111111 A
b101010101011011100000111000001011111001010101101011110001011110 J
b11111010 B
b1101111110001101100101100111011000100011001101010000010001110000 K
b0 C
b100111011010011101001001010011000101011001100001001101110011110 L
b11111010 D
b1000111110011101011100111101001111100100000110111111001100110011 M
b11111111 E
b1101100011101100010110101001001011100111011110101110101011110100 N
b10000001001110011111011001111111111010110001010100011111110 <
b110101100011100010 ;
b1111101111110110001100000100110000000000101010101010111111100100 $
